first/__init__.py
first/utils.py
models/__init__.py
models/alldnet.py
models/densenet.py
models/densenet3.py
models/densenet_efficient_multi_gpu.py
models/googlenet.py
models/lenet.py
models/mobilenet.py
models/resnet.py
models/resnext.py
models/vgg.py
models_new/__init__.py
models_new/densenet.py
models_new/dla.py
models_new/dla_simple.py
models_new/dpn.py
models_new/efficientnet.py
models_new/googlenet.py
models_new/lenet.py
models_new/mobilenet.py
models_new/mobilenetv2.py
models_new/pnasnet.py
models_new/preact_resnet.py
models_new/regnet.py
models_new/resnet.py
models_new/resnext.py
models_new/senet.py
models_new/shufflenet.py
models_new/shufflenetv2.py
models_new/vgg.py
mysecondazibit-0.0.1.dist-info/LICENSE
mysecondazibit-0.0.1.dist-info/METADATA
mysecondazibit-0.0.1.dist-info/WHEEL
mysecondazibit-0.0.1.dist-info/top_level.txt
mysecondazibit-0.0.1.dist-info/RECORD
